{
	"name": "Backend",
	"dockerComposeFile": [
		"../docker-compose.yaml",
		"../docker-compose.override.yaml",
		"docker-compose.yml"
	],
	"service": "app",
	"workspaceFolder": "/home/rails/app",
	"remoteUser": "rails",
	"customizations": {
		"vscode": {
			"settings": {
				"terminal.integrated.defaultProfile.linux": "zsh",
			},
			"extensions": [
				"iliazeus.vscode-ansi",
				"IBM.output-colorizer",
				"bung87.vscode-gemfile",
				"sporto.rails-go-to-spec",
				"rocketseat.theme-omni",
				"PKief.material-icon-theme",
				"donjayamanne.githistory",
				"GitHub.vscode-pull-request-github",
				"vivaxy.vscode-conventional-commits",
				"mhutchie.git-graph",
				"eamodio.gitlens",
				"Shopify.ruby-lsp"
			]
		}
	}
}